iotile_transport_bled112/__init__.py
iotile_transport_bled112/async_packet.py
iotile_transport_bled112/bgapi_structures.py
iotile_transport_bled112/bled112.py
iotile_transport_bled112/bled112_auth.py
iotile_transport_bled112/bled112_cmd.py
iotile_transport_bled112/bled112_cmd_co.py
iotile_transport_bled112/broadcast_v2_dedupe.py
iotile_transport_bled112/config_variables.py
iotile_transport_bled112/server_bled112.py
iotile_transport_bled112/tilebus.py
iotile_transport_bled112/utilities.py
iotile_transport_bled112/hardware/__init__.py
iotile_transport_bled112/hardware/emulator/__init__.py
iotile_transport_bled112/hardware/emulator/mock_adv_bled112.py
iotile_transport_bled112/hardware/emulator/mock_bled112.py
iotile_transport_bled112-3.1.0.dist-info/LICENSE.md
iotile_transport_bled112-3.1.0.dist-info/METADATA
iotile_transport_bled112-3.1.0.dist-info/WHEEL
iotile_transport_bled112-3.1.0.dist-info/entry_points.txt
iotile_transport_bled112-3.1.0.dist-info/top_level.txt
iotile_transport_bled112-3.1.0.dist-info/RECORD
